sockit/__init__.py
sockit/__main__.py
sockit/asciitrans/__init__.py
sockit/compare/__init__.py
sockit/data/__init__.py
sockit/data/index_skills.csv
sockit/data/index_soc4s.csv
sockit/data/index_socs.csv
sockit/data/lookup_abbreviations.json
sockit/data/lookup_acronyms.json
sockit/data/lookup_resume_headers.json
sockit/data/lookup_soc4_titles.json
sockit/data/lookup_soc_titles.json
sockit/data/matrix_soc_skill.txt
sockit/data/model_soc4.txt
sockit/data/set_job_title_nouns.txt
sockit/data/trie_alternative_titles.json
sockit/data/trie_degrees.json
sockit/data/trie_fields_of_study.json
sockit/data/trie_job_titles.json
sockit/data/trie_job_titles_override.json
sockit/data/trie_nonskills.json
sockit/data/trie_schools.json
sockit/data/trie_skills.json
sockit/data/vector_skill_idf.txt
sockit/log/__init__.py
sockit/parse/__init__.py
sockit/re/__init__.py
sockit/skillvector/__init__.py
sockit/title/__init__.py
sockit-0.3.1.dist-info/LICENSE.md
sockit-0.3.1.dist-info/METADATA
sockit-0.3.1.dist-info/WHEEL
sockit-0.3.1.dist-info/entry_points.txt
sockit-0.3.1.dist-info/top_level.txt
sockit-0.3.1.dist-info/RECORD
