Metadata-Version: 2.1
Name: sockit
Version: 0.3.1
Summary: Sockit is a natural-language processing toolkit for modeling structured occupation information and Standard Occupational Classification (SOC) codes in unstructured text from job titles, job postings, and resumes.
Home-page: https://github.com/ripl-org/sockit
Author: Mark Howison
Author-email: connect@ripl.org
License: Free for non-commercial use
Classifier: Development Status :: 3 - Alpha
Classifier: License :: Free for non-commercial use
Classifier: Intended Audience :: Science/Research
Classifier: Operating System :: OS Independent
Classifier: Natural Language :: English
Classifier: Programming Language :: Python :: 3
Classifier: Topic :: Scientific/Engineering
Classifier: Topic :: Scientific/Engineering :: Artificial Intelligence
Classifier: Topic :: Scientific/Engineering :: Human Machine Interfaces
Classifier: Topic :: Scientific/Engineering :: Information Analysis
Requires-Python: >=3.8
License-File: LICENSE.md
Requires-Dist: chardet
Requires-Dist: docx2txt
Requires-Dist: html2text
Requires-Dist: PyPDF2
Requires-Dist: numpy (>=1.0.0)
Requires-Dist: scipy (>=1.0.0)
Requires-Dist: wordtrie (>=0.0.4)
